swytcher/__init__.py
swytcher/cli.py
swytcher/config.ini
swytcher/log_conf.ini
swytcher/settings.py
swytcher/swytcher.py
swytcher/util.py
swytcher/xwindow.py
swytcher-0.3.2.dist-info/DESCRIPTION.rst
swytcher-0.3.2.dist-info/METADATA
swytcher-0.3.2.dist-info/RECORD
swytcher-0.3.2.dist-info/WHEEL
swytcher-0.3.2.dist-info/entry_points.txt
swytcher-0.3.2.dist-info/metadata.json
swytcher-0.3.2.dist-info/top_level.txt
