Metadata-Version: 2.0
Name: swytcher
Version: 0.3.2
Summary: Automatically switch layout based on your active window
Home-page: https://github.com/eddie-dunn/swytcher
Author: Eddie Dunn
Author-email: eddie.dunn@gmail.com
License: MIT license
Keywords: keyboard layout switcher
Platform: UNKNOWN
Classifier: Development Status :: 2 - Pre-Alpha
Classifier: Intended Audience :: Developers
Classifier: License :: OSI Approved :: MIT License
Classifier: Natural Language :: English
Classifier: Programming Language :: Python :: 3
Classifier: Programming Language :: Python :: 3.4
Classifier: Programming Language :: Python :: 3.5
Classifier: Programming Language :: Python :: 3.6
Requires-Python: >=3
Requires-Dist: click (>=6.0)
Requires-Dist: python-xlib
Requires-Dist: xkbgroup
